{"lastUsed":1649919342883,"path":"E:\/program\/Java web\/Learn","projectCount":1,"recentFiles":[{"path":"\/pro2004\/src\/main\/webapp\/login","parentWorkspace":"E:\/program\/Java web\/Learn","name":"login.jsp","lastModified":1649217245148,"locationURI":"file:\/E:\/program\/Java%20web\/Learn\/pro2004\/src\/main\/webapp\/login\/login.jsp"},{"path":"\/pro2004\/Java Resource\/action","parentWorkspace":"E:\/program\/Java web\/Learn","name":"GetCurUser.java","lastModified":1649917600251,"locationURI":"file:\/E:\/program\/Java%20web\/Learn\/pro2004\/Java%20Resource\/action\/GetCurUser.java"},{"path":"\/pro2004\/Java Resource\/action","parentWorkspace":"E:\/program\/Java web\/Learn","name":"UpdateServlet.java","lastModified":1649763203427,"locationURI":"file:\/E:\/program\/Java%20web\/Learn\/pro2004\/Java%20Resource\/action\/UpdateServlet.java"},{"path":"\/pro2004\/src\/main\/webapp\/login","parentWorkspace":"E:\/program\/Java web\/Learn","name":"result.jsp","lastModified":1649919273535,"locationURI":"file:\/E:\/program\/Java%20web\/Learn\/pro2004\/src\/main\/webapp\/login\/result.jsp"},{"path":"\/pro2004\/Java Resource\/action","parentWorkspace":"E:\/program\/Java web\/Learn","name":"regServlet.java","lastModified":1649763053525,"locationURI":"file:\/E:\/program\/Java%20web\/Learn\/pro2004\/Java%20Resource\/action\/regServlet.java"},{"path":"\/pro2004\/src\/main\/webapp","parentWorkspace":"E:\/program\/Java web\/Learn","name":"index.jsp","lastModified":1647485788913,"locationURI":"file:\/E:\/program\/Java%20web\/Learn\/pro2004\/src\/main\/webapp\/index.jsp"},{"path":"\/Servers\/Tomcat v10.0 Server at localhost-config","parentWorkspace":"E:\/program\/Java web\/Learn","name":"server.xml","lastModified":1649745866684,"locationURI":"file:\/E:\/program\/Java%20web\/Learn\/Servers\/Tomcat%20v10.0%20Server%20at%20localhost-config\/server.xml"},{"path":"\/pro2004\/src\/main\/webapp\/login","parentWorkspace":"E:\/program\/Java web\/Learn","name":"update.jsp","lastModified":1649917793465,"locationURI":"file:\/E:\/program\/Java%20web\/Learn\/pro2004\/src\/main\/webapp\/login\/update.jsp"},{"path":"\/Servers\/Tomcat v10.0 Server at localhost-config","parentWorkspace":"E:\/program\/Java web\/Learn","name":"web.xml","lastModified":1649916858308,"locationURI":"file:\/E:\/program\/Java%20web\/Learn\/Servers\/Tomcat%20v10.0%20Server%20at%20localhost-config\/web.xml"},{"path":"\/pro2004\/Java Resource\/action","parentWorkspace":"E:\/program\/Java web\/Learn","name":"GetUserServlet.java","lastModified":1649917600251,"locationURI":"file:\/E:\/program\/Java%20web\/Learn\/pro2004\/Java%20Resource\/action\/GetUserServlet.java"},{"path":"\/pro2004\/src\/main\/webapp\/login","parentWorkspace":"E:\/program\/Java web\/Learn","name":"dologin.jsp","lastModified":1647494074237,"locationURI":"file:\/E:\/program\/Java%20web\/Learn\/pro2004\/src\/main\/webapp\/login\/dologin.jsp"},{"path":"\/pro2004\/Java Resource\/action","parentWorkspace":"E:\/program\/Java web\/Learn","name":"DelUser.java","lastModified":1649762509489,"locationURI":"file:\/E:\/program\/Java%20web\/Learn\/pro2004\/Java%20Resource\/action\/DelUser.java"},{"path":"\/pro2004\/Java Resource\/dao","parentWorkspace":"E:\/program\/Java web\/Learn","name":"BaseDao.java","lastModified":1649763180829,"locationURI":"file:\/E:\/program\/Java%20web\/Learn\/pro2004\/Java%20Resource\/dao\/BaseDao.java"},{"path":"\/pro2004\/src\/main\/webapp\/reg","parentWorkspace":"E:\/program\/Java web\/Learn","name":"reg.jsp","lastModified":1649326149680,"locationURI":"file:\/E:\/program\/Java%20web\/Learn\/pro2004\/src\/main\/webapp\/reg\/reg.jsp"},{"path":"\/pro2004\/Java Resource\/action","parentWorkspace":"E:\/program\/Java web\/Learn","name":"LoginServlet.java","lastModified":1649762878830,"locationURI":"file:\/E:\/program\/Java%20web\/Learn\/pro2004\/Java%20Resource\/action\/LoginServlet.java"},{"path":"\/pro2004\/src\/main\/webapp\/reg","parentWorkspace":"E:\/program\/Java web\/Learn","name":"result.jsp","lastModified":1649322808285,"locationURI":"file:\/E:\/program\/Java%20web\/Learn\/pro2004\/src\/main\/webapp\/reg\/result.jsp"},{"path":"\/pro2004\/Java Resource\/entity","parentWorkspace":"E:\/program\/Java web\/Learn","name":"User.java","lastModified":1649917537508,"locationURI":"file:\/E:\/program\/Java%20web\/Learn\/pro2004\/Java%20Resource\/entity\/User.java"}]}